whale_diamond/__init__.py
whale_diamond-0.1.0.dist-info/DESCRIPTION.rst
whale_diamond-0.1.0.dist-info/METADATA
whale_diamond-0.1.0.dist-info/RECORD
whale_diamond-0.1.0.dist-info/WHEEL
whale_diamond-0.1.0.dist-info/metadata.json
whale_diamond-0.1.0.dist-info/top_level.txt
