Metadata-Version: 2.0
Name: whale-diamond
Version: 0.1.0
Summary: Whale Monitoring Diamond Handler
Home-page: git@github.com:WhaleMonitoring/whale-diamond.git
Author: Whale Monitoring
Author-email: eirik@sylliaas.no
License: MIT
Keywords: Monitoring,Linux,Whale
Platform: UNKNOWN
Classifier: Intended Audience :: Developers
Classifier: License :: OSI Approved :: MIT License
Classifier: Natural Language :: English
Classifier: Programming Language :: Python :: 2
Classifier: Programming Language :: Python :: 2.7
Requires-Dist: six
Requires-Dist: whale-api
